mercure/__init__.py
mercure/client/__init__.py
mercure/client/publisher/__init__.py
mercure/client/publisher/asynchronous.py
mercure/client/publisher/base.py
mercure/client/publisher/common.py
mercure/client/publisher/gevent.py
mercure/client/publisher/tests/__init__.py
mercure/client/publisher/tests/test_base.py
mercure/client/subscriber/__init__.py
mercure-0.0.2.0.dist-info/WHEEL
mercure-0.0.2.0.dist-info/METADATA
mercure-0.0.2.0.dist-info/RECORD
